og_learn/__init__.py
og_learn/density.py
og_learn/evaluation.py
og_learn/feature.py
og_learn/framework.py
og_learn/og_core.py
og_learn/presets.py
og_learn/split.py
og_learn/utils.py
og_learn/models/__init__.py
og_learn/models/mlp.py
og_learn/models/resnet.py
og_learn/models/transformer.py
og_learn-1.0.0.dist-info/licenses/LICENSE
og_learn-1.0.0.dist-info/METADATA
og_learn-1.0.0.dist-info/WHEEL
og_learn-1.0.0.dist-info/top_level.txt
og_learn-1.0.0.dist-info/RECORD
