Metadata-Version: 2.4
Name: og-learn
Version: 1.0.0
Summary: Overfit-to-Generalization Framework for Equitable Spatiotemporal Modeling
Author-email: Zhehao Liang <zliang7@nd.edu>
Maintainer-email: Zhehao Liang <zliang7@nd.edu>
License-Expression: MIT
Project-URL: Homepage, https://github.com/px39n/og-learn
Project-URL: Documentation, https://px39n.github.io/og-learn/
Project-URL: Repository, https://github.com/px39n/og-learn
Project-URL: Issues, https://github.com/px39n/og-learn/issues
Keywords: machine learning,spatiotemporal,overfitting,generalization,spatial equity,environmental modeling
Classifier: Development Status :: 3 - Alpha
Classifier: Intended Audience :: Science/Research
Classifier: Operating System :: OS Independent
Classifier: Programming Language :: Python :: 3
Classifier: Programming Language :: Python :: 3.8
Classifier: Programming Language :: Python :: 3.9
Classifier: Programming Language :: Python :: 3.10
Classifier: Programming Language :: Python :: 3.11
Classifier: Topic :: Scientific/Engineering :: Artificial Intelligence
Classifier: Topic :: Scientific/Engineering :: Atmospheric Science
Requires-Python: >=3.8
License-File: LICENSE
Requires-Dist: numpy>=1.21.0
Requires-Dist: pandas>=1.3.0
Requires-Dist: scikit-learn>=1.0.0
Requires-Dist: torch>=1.10.0
Requires-Dist: lightgbm>=3.3.0
Provides-Extra: dev
Requires-Dist: pytest>=7.0.0; extra == "dev"
Requires-Dist: pytest-cov>=4.0.0; extra == "dev"
Requires-Dist: black>=23.0.0; extra == "dev"
Requires-Dist: isort>=5.12.0; extra == "dev"
Requires-Dist: flake8>=6.0.0; extra == "dev"
Provides-Extra: all
Requires-Dist: xgboost>=1.6.0; extra == "all"
Requires-Dist: catboost>=1.0.0; extra == "all"
Dynamic: license-file
